tensorflow_hmm
