Metadata-Version: 1.0
Name: tensorflow-hmm
Version: 0.2.1
Summary: Tensorflow and numpy implementations of the HMM viterbi and forward/backward algorithms
Home-page: http://github.com/dwiel/tensorflow_hmm
Author: Zach Dwiel
Author-email: zdwiel@gmail.com
License: Apache
Platform: UNKNOWN
